[
  {
    "id": "1622792475246112770",
    "createUser": "1123598821738675201",
    "createDept": "1564479552429559809",
    "createTime": "2023-02-07 11:00:51",
    "updateUser": "1123598821738675201",
    "updateTime": "2024-03-01 14:34:10",
    "status": 1,
    "isDeleted": 0,
    "tenantId": "000000",
    "code": "screen",
    "name": "全景监视",
    "source": "iconfont iconicon_glass",
    "sort": 1,
    "children": [
      {
        "id": "1781149655000219650",
        "parentId": "0",
        "code": "screen",
        "name": "风场监测",
        "alias": "menu",
        "path": "/screen",
        "source": "iconfont iconicon_airplay",
        "sort": 1,
        "category": 1,
        "action": 0,
        "isOpen": 1,
        "remark": "",
        "isDeleted": 0,
        "hasChildren": false,
        "parentName": "",
        "categoryName": "",
        "actionName": "",
        "isOpenName": ""
      },
      {
        "id": "1781153806815920130",
        "parentId": "0",
        "code": "turbine",
        "name": "机组监测",
        "alias": "menu",
        "path": "/WindTurbine",
        "source": "iconfont iconicon_airplay",
        "sort": 2,
        "category": 1,
        "action": 0,
        "isOpen": 1,
        "remark": "",
        "isDeleted": 0,
        "hasChildren": false,
        "parentName": "",
        "categoryName": "",
        "actionName": "",
        "isOpenName": ""
      }
    ]
  },
  {
    "id": "1626399341670871041",
    "createUser": "1123598821738675201",
    "createDept": "1564479552429559809",
    "createTime": "2023-02-17 09:53:15",
    "updateUser": "1123598821738675201",
    "updateTime": "2024-03-01 14:34:20",
    "status": 1,
    "isDeleted": 0,
    "tenantId": "000000",
    "code": "analysis",
    "name": "诊断分析",
    "source": "iconfont iconicon_compile",
    "sort": 2,
    "children": [
      {
        "id": "1819253628223422466",
        "parentId": "0",
        "code": "customAnalysisNew",
        "name": "智能诊断",
        "alias": "menu",
        "path": "/customAnalysisNew",
        "source": "iconfont icon-rizhi1",
        "sort": 1,
        "category": 1,
        "action": 0,
        "isOpen": 1,
        "remark": "",
        "isDeleted": 0,
        "hasChildren": false,
        "parentName": "",
        "categoryName": "",
        "actionName": "",
        "isOpenName": ""
      }
    ]
  },
  {
    "id": "1951197271603007490",
    "createUser": "1123598821738675201",
    "createDept": "1948618828071817217",
    "createTime": "2025-08-01 16:24:16",
    "updateUser": "1123598821738675201",
    "updateTime": "2025-09-29 16:56:19",
    "status": 1,
    "isDeleted": 0,
    "tenantId": "",
    "code": "report",
    "name": "诊断报告",
    "source": "iconfont iconicon_doc",
    "sort": 3,
    "children": [
      {
        "id": "1665619879795478529",
        "parentId": "0",
        "code": "diagnosticTasks",
        "name": "报告工作台",
        "alias": "menu",
        "path": "/diagnosticTasks",
        "source": "iconfont iconicon_doc",
        "sort": 3,
        "category": 1,
        "action": 0,
        "isOpen": 1,
        "remark": "",
        "isDeleted": 0,
        "hasChildren": false,
        "parentName": "",
        "categoryName": "",
        "actionName": "",
        "isOpenName": ""
      },
      {
        "id": "1670660059294658562",
        "parentId": "0",
        "code": "reportManage",
        "name": "报告管理",
        "alias": "menu",
        "path": "/reportManage",
        "source": "iconfont iconicon_study",
        "sort": 4,
        "category": 1,
        "action": 0,
        "isOpen": 1,
        "remark": "",
        "isDeleted": 0,
        "hasChildren": false,
        "parentName": "",
        "categoryName": "",
        "actionName": "",
        "isOpenName": ""
      }
    ]
  },
  {
    "id": "1972232153824878594",
    "createUser": "1123598821738675201",
    "createDept": "1948618828071817217",
    "createTime": "2025-09-28 17:29:22",
    "updateUser": "1123598821738675201",
    "updateTime": "2025-10-15 14:32:34",
    "status": 1,
    "isDeleted": 0,
    "tenantId": "",
    "code": "basicConfig",
    "name": "数据下载",
    "source": "iconfont iconicon_work",
    "sort": 4,
    "children": [
      {
        "id": "1972230964462870529",
        "parentId": "0",
        "code": "dataDownLoad",
        "name": "数据下载",
        "alias": "menu",
        "path": "/basicConfig/dataDownLoad",
        "source": "iconfont icon-wxbgongju",
        "sort": 1,
        "category": 1,
        "action": 0,
        "isOpen": 1,
        "remark": "",
        "isDeleted": 0,
        "hasChildren": false,
        "parentName": "",
        "categoryName": "",
        "actionName": "",
        "isOpenName": ""
      }
    ]
  },
  {
    "id": "1972524853824873608",
    "createUser": "1123598821738675201",
    "createDept": "1948618828071817217",
    "createTime": "2025-09-28 17:29:22",
    "updateUser": "1123598821738675201",
    "updateTime": "2025-10-15 14:32:34",
    "status": 1,
    "isDeleted": 0,
    "tenantId": "",
    "code": "opsSystem",
    "name": "运维管理",
    "source": "iconfont iconicon_work",
    "sort": 5,
    "children": [
      {
        "id": "1972231263214755841",
        "parentId": "0",
        "code": "dauData",
        "name": "系统自检",
        "alias": "menu",
        "path": "/basicConfig/dauData",
        "source": "iconfont iconicon_compile",
        "sort": 15,
        "category": 1,
        "action": 0,
        "isOpen": 1,
        "remark": "",
        "isDeleted": 0,
        "hasChildren": false,
        "parentName": "",
        "categoryName": "",
        "actionName": "",
        "isOpenName": ""
      },
      {
        "id": "1979079406711574530",
        "parentId": "0",
        "code": "dauConfigHandle",
        "name": "测点通道配置",
        "alias": "menu",
        "path": "/basicConfig/dauConfigHandle",
        "source": "iconfont iconicon_work",
        "sort": 18,
        "category": 1,
        "action": 0,
        "isOpen": 1,
        "remark": "",
        "isDeleted": 0,
        "hasChildren": false,
        "parentName": "",
        "categoryName": "",
        "actionName": "",
        "isOpenName": ""
      }
    ]
  },
  {
    "id": "1669264578089906177",
    "createUser": "1123598821738675201",
    "createDept": "1564479552429559809",
    "createTime": "2023-06-15 16:44:24",
    "updateUser": "1123598821738675201",
    "updateTime": "2025-09-29 16:56:12",
    "status": 1,
    "isDeleted": 0,
    "tenantId": "000000",
    "code": "system",
    "name": "系统管理",
    "source": "iconfont iconicon_setting",
    "sort": 6,
    "children": [
      {
        "id": "1620968366407729153",
        "parentId": "0",
        "code": "equipment ",
        "name": "设备管理",
        "alias": "menu",
        "path": "/equipment",
        "source": "iconfont iconicon_work",
        "sort": 1,
        "category": 1,
        "action": 0,
        "isOpen": 1,
        "remark": "",
        "isDeleted": 0,
        "children": [
          {
            "id": "1620969188961075201",
            "parentId": "1620968366407729153",
            "code": "equipment_turbine",
            "name": "风机管理",
            "alias": "menu",
            "path": "/equipment/turbine/index",
            "source": "iconfont iconicon_compile",
            "sort": 1,
            "category": 1,
            "action": 0,
            "isOpen": 1,
            "remark": "",
            "isDeleted": 0,
            "hasChildren": false,
            "parentName": "",
            "categoryName": "",
            "actionName": "",
            "isOpenName": ""
          },
          {
            "id": "1676149858635468802",
            "parentId": "1620968366407729153",
            "code": "equipment_component",
            "name": "部件管理",
            "alias": "menu",
            "path": "/equipment/component/index",
            "source": "iconfont iconicon_coinpurse_line",
            "sort": 2,
            "category": 1,
            "action": 0,
            "isOpen": 1,
            "remark": "",
            "isDeleted": 0,
            "hasChildren": false,
            "parentName": "",
            "categoryName": "",
            "actionName": "",
            "isOpenName": ""
          },
          {
            "id": "1978351871535190017",
            "parentId": "1620968366407729153",
            "code": "dauconfig",
            "name": "采集单元配置",
            "alias": "menu",
            "path": "/equipment/dau/index",
            "source": "iconfont iconicon_setting",
            "sort": 3,
            "category": 1,
            "action": 0,
            "isOpen": 1,
            "remark": "",
            "isDeleted": 0,
            "hasChildren": false,
            "parentName": "",
            "categoryName": "",
            "actionName": "",
            "isOpenName": ""
          },
          {
            "id": "1676150983463915522",
            "parentId": "1620968366407729153",
            "code": "equipment_unit",
            "name": "采集单元管理",
            "alias": "menu",
            "path": "/equipment/unit/index",
            "source": "iconfont iconicon_send",
            "sort": 4,
            "category": 1,
            "action": 0,
            "isOpen": 1,
            "remark": "",
            "isDeleted": 0,
            "hasChildren": false,
            "parentName": "",
            "categoryName": "",
            "actionName": "",
            "isOpenName": ""
          },
          {
            "id": "1747854486205431809",
            "parentId": "1620968366407729153",
            "code": "equipment_model",
            "name": "设备模型管理",
            "alias": "menu",
            "path": "/equipment/model/index",
            "source": "iconfont iconicon_airplay",
            "sort": 5,
            "category": 1,
            "action": 0,
            "isOpen": 1,
            "remark": "",
            "isDeleted": 0,
            "hasChildren": false,
            "parentName": "",
            "categoryName": "",
            "actionName": "",
            "isOpenName": ""
          }
        ],
        "hasChildren": false,
        "parentName": "",
        "categoryName": "",
        "actionName": "",
        "isOpenName": ""
      },
      {
        "id": "1769546501359992833",
        "parentId": "0",
        "code": "bearingManage",
        "name": "轴承管理",
        "alias": "menu",
        "path": "/bearingManage",
        "source": "iconfont iconicon_coinpurse_line",
        "sort": 5,
        "category": 1,
        "action": 0,
        "isOpen": 1,
        "remark": "",
        "isDeleted": 0,
        "children": [
          {
            "id": "1769546930772836353",
            "parentId": "1769546501359992833",
            "code": "equipmentManage",
            "name": "轴承设备管理",
            "alias": "menu",
            "path": "/bearingManage/equipmentManage",
            "source": "iconfont iconicon_compile",
            "sort": 1,
            "category": 1,
            "action": 0,
            "isOpen": 1,
            "remark": "",
            "isDeleted": 0,
            "hasChildren": false,
            "parentName": "",
            "categoryName": "",
            "actionName": "",
            "isOpenName": ""
          },
          {
            "id": "1769547197664788482",
            "parentId": "1769546501359992833",
            "code": "faultManage",
            "name": "轴承故障知识库",
            "alias": "menu",
            "path": "/bearingManage/faultManage",
            "source": "iconfont iconicon_glass",
            "sort": 2,
            "category": 1,
            "action": 0,
            "isOpen": 1,
            "remark": "",
            "isDeleted": 0,
            "hasChildren": false,
            "parentName": "",
            "categoryName": "",
            "actionName": "",
            "isOpenName": ""
          }
        ],
        "hasChildren": false,
        "parentName": "",
        "categoryName": "",
        "actionName": "",
        "isOpenName": ""
      },
      {
        "id": "1676153182050963457",
        "parentId": "0",
        "code": "spotManage",
        "name": "测点",
        "alias": "menu",
        "path": "/spotManage",
        "source": "iconfont iconicon_discovery",
        "sort": 5,
        "category": 1,
        "action": 0,
        "isOpen": 1,
        "remark": "",
        "isDeleted": 0,
        "children": [
          {
            "id": "1676153648038137857",
            "parentId": "1676153182050963457",
            "code": "spotManage_spot",
            "name": "测点管理",
            "alias": "menu",
            "path": "/spotManage/spot/index",
            "source": "iconfont iconicon_addresslist",
            "sort": 1,
            "category": 1,
            "action": 0,
            "isOpen": 1,
            "remark": "",
            "isDeleted": 0,
            "hasChildren": false,
            "parentName": "",
            "categoryName": "",
            "actionName": "",
            "isOpenName": ""
          }
        ],
        "hasChildren": false,
        "parentName": "",
        "categoryName": "",
        "actionName": "",
        "isOpenName": ""
      },
      {
        "id": "1686566399131582465",
        "parentId": "0",
        "code": "alarmFault",
        "name": "模型管理",
        "alias": "menu",
        "path": "/alarmFault",
        "source": "iconfont iconicon_affiliations_li",
        "sort": 6,
        "category": 1,
        "action": 0,
        "isOpen": 1,
        "remark": "",
        "isDeleted": 0,
        "children": [
          {
            "id": "1686567612824748033",
            "parentId": "1686566399131582465",
            "code": "deviceTree",
            "name": "故障树",
            "alias": "menu",
            "path": "/alarmFault/deviceTree/index",
            "source": "iconfont iconicon_scan",
            "sort": 1,
            "category": 1,
            "action": 0,
            "isOpen": 1,
            "remark": "",
            "isDeleted": 0,
            "hasChildren": false,
            "parentName": "",
            "categoryName": "",
            "actionName": "",
            "isOpenName": ""
          },
          {
            "id": "1686567333664456706",
            "parentId": "1686566399131582465",
            "code": "alarmMode",
            "name": "报警模型",
            "alias": "menu",
            "path": "/alarmFault/alarmModel/index",
            "source": "iconfont iconicon_subordinate",
            "sort": 2,
            "category": 1,
            "action": 0,
            "isOpen": 1,
            "remark": "",
            "isDeleted": 0,
            "hasChildren": false,
            "parentName": "",
            "categoryName": "",
            "actionName": "",
            "isOpenName": ""
          }
        ],
        "hasChildren": false,
        "parentName": "",
        "categoryName": "",
        "actionName": "",
        "isOpenName": ""
      },
      {
        "id": "1747854986841751554",
        "parentId": "0",
        "code": "monitorMeasure",
        "name": "监测方案",
        "alias": "menu",
        "path": "/monitorMeasurePoint",
        "source": "iconfont iconicon_doc",
        "sort": 10,
        "category": 1,
        "action": 0,
        "isOpen": 1,
        "remark": "",
        "isDeleted": 0,
        "children": [
          {
            "id": "1747855337745612802",
            "parentId": "1747854986841751554",
            "code": "monitorMeasurePoint",
            "name": "监测方案管理",
            "alias": "menu",
            "path": "/monitorMeasurePoint/config",
            "source": "iconfont iconicon_dispose",
            "sort": 1,
            "category": 1,
            "action": 0,
            "isOpen": 1,
            "remark": "",
            "isDeleted": 0,
            "hasChildren": false,
            "parentName": "",
            "categoryName": "",
            "actionName": "",
            "isOpenName": ""
          }
        ],
        "hasChildren": false,
        "parentName": "",
        "categoryName": "",
        "actionName": "",
        "isOpenName": ""
      },
      {
        "id": "1123598815738675203",
        "parentId": "0",
        "code": "system",
        "name": "系统管理",
        "alias": "menu",
        "path": "/system",
        "source": "iconfont iconicon_setting",
        "sort": 99,
        "category": 1,
        "action": 0,
        "isOpen": 1,
        "remark": "",
        "isDeleted": 0,
        "children": [
          {
            "id": "1123598815738675204",
            "parentId": "1123598815738675203",
            "code": "user",
            "name": "账号管理",
            "alias": "menu",
            "path": "/system/user",
            "source": "iconfont iconicon_principal",
            "sort": 1,
            "category": 1,
            "action": 0,
            "isOpen": 1,
            "remark": "",
            "isDeleted": 0,
            "hasChildren": false,
            "parentName": "",
            "categoryName": "",
            "actionName": "",
            "isOpenName": ""
          },
          {
            "id": "1123598815738675308",
            "parentId": "1123598815738675203",
            "code": "role",
            "name": "角色管理",
            "alias": "menu",
            "path": "/authority/role",
            "source": "iconfont iconicon_boss",
            "sort": 1,
            "category": 1,
            "action": 0,
            "isOpen": 1,
            "remark": "",
            "isDeleted": 0,
            "hasChildren": false,
            "parentName": "",
            "categoryName": "",
            "actionName": "",
            "isOpenName": ""
          },
          {
            "id": "1164733399668962202",
            "parentId": "1123598815738675203",
            "code": "region",
            "name": "行政区划",
            "alias": "menu",
            "path": "/base/region",
            "source": "iconfont icon-iframe",
            "sort": 1,
            "category": 1,
            "action": 0,
            "isOpen": 1,
            "remark": "",
            "isDeleted": 0,
            "hasChildren": false,
            "parentName": "",
            "categoryName": "",
            "actionName": "",
            "isOpenName": ""
          },
          {
            "id": "1123598815738675205",
            "parentId": "1123598815738675203",
            "code": "dept",
            "name": "风场管理",
            "alias": "menu",
            "path": "/system/dept",
            "source": "iconfont iconicon_group",
            "sort": 2,
            "category": 1,
            "action": 0,
            "isOpen": 1,
            "remark": "",
            "isDeleted": 0,
            "hasChildren": false,
            "parentName": "",
            "categoryName": "",
            "actionName": "",
            "isOpenName": ""
          },
          {
            "id": "1123598815738675206",
            "parentId": "1123598815738675203",
            "code": "dict",
            "name": "系统字典",
            "alias": "menu",
            "path": "/system/dict",
            "source": "iconfont iconicon_addresslist",
            "sort": 4,
            "category": 1,
            "action": 0,
            "isOpen": 1,
            "remark": "",
            "isDeleted": 0,
            "hasChildren": false,
            "parentName": "",
            "categoryName": "",
            "actionName": "",
            "isOpenName": ""
          },
          {
            "id": "1164733379658963251",
            "parentId": "1123598815738675203",
            "code": "dictbiz",
            "name": "业务字典",
            "alias": "menu",
            "path": "/system/dictbiz",
            "source": "iconfont iconicon_study",
            "sort": 5,
            "category": 1,
            "action": 0,
            "isOpen": 1,
            "remark": "",
            "isDeleted": 0,
            "hasChildren": false,
            "parentName": "",
            "categoryName": "",
            "actionName": "",
            "isOpenName": ""
          },
          {
            "id": "1123598815738675207",
            "parentId": "1123598815738675203",
            "code": "menu",
            "name": "菜单管理",
            "alias": "menu",
            "path": "/system/menu",
            "source": "iconfont iconicon_subordinate",
            "sort": 6,
            "category": 1,
            "action": 0,
            "isOpen": 1,
            "remark": "",
            "isDeleted": 0,
            "hasChildren": false,
            "parentName": "",
            "categoryName": "",
            "actionName": "",
            "isOpenName": ""
          },
          {
            "id": "1622789532920885250",
            "parentId": "1123598815738675203",
            "code": "topmenu",
            "name": "顶部菜单",
            "alias": "menu",
            "path": "/system/topmenu",
            "source": "iconfont icon-canshu",
            "sort": 7,
            "category": 1,
            "action": 0,
            "isOpen": 1,
            "remark": "",
            "isDeleted": 0,
            "hasChildren": false,
            "parentName": "",
            "categoryName": "",
            "actionName": "",
            "isOpenName": ""
          }
        ],
        "hasChildren": false,
        "parentName": "",
        "categoryName": "",
        "actionName": "",
        "isOpenName": ""
      }
    ]
  }
]